Metadata-Version: 2.1
Name: polish-genbank
Version: 0.0.2
Summary: To check for the internal stop codon in Genbank or FASTA file (CDS), then substitute the internal stop codon with NNN.
Home-page: https://github.com/linzhi2013/polish_genbank
Author: Guanliang Meng
Author-email: mengguanliang@genomics.cn
License: UNKNOWN
Platform: UNKNOWN
Classifier: Development Status :: 3 - Alpha
Classifier: Intended Audience :: Science/Research
Classifier: Topic :: Scientific/Engineering :: Bio-Informatics
Classifier: License :: OSI Approved :: GNU General Public License v3 or later (GPLv3+)
Classifier: Programming Language :: Python :: 3
Classifier: Operating System :: MacOS :: MacOS X
Classifier: Operating System :: Microsoft :: Windows
Classifier: Operating System :: POSIX :: Linux
Requires-Python: >=3.4
